twita/__init__.py
twita-0.0.2.dist-info/LICENSE
twita-0.0.2.dist-info/WHEEL
twita-0.0.2.dist-info/METADATA
twita-0.0.2.dist-info/RECORD
