Metadata-Version: 2.1
Name: twita
Version: 0.0.2
Summary: Twitter Hidden API Library
Home-page: https://github.com/CounterTek/twita
License: LGPL-3.0-or-later
Keywords: twitter,twitter api
Author: DaRekaze
Author-email: darekaze@gmail.com
Requires-Python: >=3.8,<4.0
Classifier: Intended Audience :: Developers
Classifier: License :: OSI Approved :: GNU Lesser General Public License v3 or later (LGPLv3+)
Classifier: Programming Language :: Python :: 3
Classifier: Programming Language :: Python :: 3.10
Classifier: Programming Language :: Python :: 3.8
Classifier: Programming Language :: Python :: 3.9
Classifier: Programming Language :: Python :: Implementation :: CPython
Classifier: Topic :: Software Development :: Libraries :: Python Modules
Requires-Dist: aiometer (>=0.3.0)
Requires-Dist: httpx[socks,http2] (>=0.21.0)
Project-URL: Change Log, https://github.com/countertek/twita/blob/main/CHANGELOG.md
Project-URL: Repository, https://github.com/CounterTek/twita
